Metadata-Version: 2.1
Name: lc-django-ckeditor
Version: 5.6.8
Summary: Django admin CKEditor integration.
Home-page: https://github.com/LeetCode-OpenSource/django-ckeditor
Author: Shaun Sephton & Piotr Malinski
Author-email: riklaunim@gmail.com
License: UNKNOWN
Platform: UNKNOWN
Classifier: Programming Language :: Python
Classifier: Programming Language :: Python :: 2.7
Classifier: Programming Language :: Python :: 3.3
Classifier: Programming Language :: Python :: 3.4
Classifier: Programming Language :: Python :: 3.5
Classifier: Programming Language :: Python :: 3.6
Classifier: License :: OSI Approved :: BSD License
Classifier: Operating System :: OS Independent
Classifier: Framework :: Django
Classifier: Intended Audience :: Developers
Classifier: Topic :: Internet :: WWW/HTTP :: Dynamic Content
Requires-Dist: django-js-asset
